{
	"$schema": "https://json-schema.org/draft/2019-09/schema",
	"type": "object",
	"properties": {
		"payrollTotalEmployees": {
			"description": "Total UVG payroll OA for the entire personnel group in CHF (male and female)",
			"$ref": "../../../../Generics/v1.0.0/MonetaryAmountType.json"
		},
		"UVGPayrollMaleOA": {
			"description": "UVG payroll male OA",
			"$ref": "../../../../Generics/v1.0.0/MonetaryAmountType.json"
		},
		"UVGPayrollFemaleOA": {
			"description": "UVG payroll female OA",
			"$ref": "../../../../Generics/v1.0.0/MonetaryAmountType.json"
		},
		"UVGPayrollMaleNOA": {
			"description": "UVG payroll male NOA",
			"$ref": "../../../../Generics/v1.0.0/MonetaryAmountType.json"
		},
		"UVGPayrollFemaleNOA": {
			"description": "UVG payroll female NOA",
			"$ref": "../../../../Generics/v1.0.0/MonetaryAmountType.json"
		},
		"surplusPayrollTotal": {
			"description": "Total surplus payroll OA for the entire personnel group in CHF (male and female)",
			"$ref": "../../../../Generics/v1.0.0/MonetaryAmountType.json"
		},
		"surplusPayrollMaleOA": {
			"description": "Surplus payroll male OA",
			"$ref": "../../../../Generics/v1.0.0/MonetaryAmountType.json"
		},
		"surplusPayrollFemaleOA": {
			"description": "Surplus payroll male NOA",
			"$ref": "../../../../Generics/v1.0.0/MonetaryAmountType.json"
		},
		"surplusPayrollMaleNOA": {
			"description": "Surplus payroll female OA",
			"$ref": "../../../../Generics/v1.0.0/MonetaryAmountType.json"
		},
		"surplusPayrollFemaleNOA": {
			"description": "Surplus payroll female NOA",
			"$ref": "../../../../Generics/v1.0.0/MonetaryAmountType.json"
		}
	},
	"additionalProperties": false,
	"required": [
		"payrollTotalEmployees",
		"surplusPayrollTotal"
	]
}